{"nodes": [{"id": "roadmap_SecurityFeatures", "label": "Security Features Track", "file_type": "document", "source_file": "ROADMAP.md", "source_location": null, "source_url": null, "captured_at": null, "author": null, "contributor": null}, {"id": "roadmap_StabilityFeatures", "label": "Stability Features Track", "file_type": "document", "source_file": "ROADMAP.md", "source_location": null, "source_url": null, "captured_at": null, "author": null, "contributor": null}, {"id": "roadmap_UXUIFeatures", "label": "UX/UI Improvements Track", "file_type": "document", "source_file": "ROADMAP.md", "source_location": null, "source_url": null, "captured_at": null, "author": null, "contributor": null}, {"id": "roadmap_Leaderboard", "label": "Viewer Leaderboard", "file_type": "document", "source_file": "ROADMAP.md", "source_location": null, "source_url": null, "captured_at": null, "author": null, "contributor": null}, {"id": "roadmap_PointsSystem", "label": "Points/Coins System", "file_type": "document", "source_file": "ROADMAP.md", "source_location": null, "source_url": null, "captured_at": null, "author": null, "contributor": null}, {"id": "roadmap_SFXAlerts", "label": "SFX Alert Sounds", "file_type": "document", "source_file": "ROADMAP.md", "source_location": null, "source_url": null, "captured_at": null, "author": null, "contributor": null}, {"id": "roadmap_OBSWebSocket", "label": "OBS WebSocket Integration", "file_type": "document", "source_file": "ROADMAP.md", "source_location": null, "source_url": null, "captured_at": null, "author": null, "contributor": null}, {"id": "roadmap_WelcomeMessages", "label": "Welcome Messages Feature", "file_type": "document", "source_file": "ROADMAP.md", "source_location": null, "source_url": null, "captured_at": null, "author": null, "contributor": null}, {"id": "roadmap_BackupSystem", "label": "Auto Backup System", "file_type": "document", "source_file": "ROADMAP.md", "source_location": null, "source_url": null, "captured_at": null, "author": null, "contributor": null}, {"id": "roadmap_PluginSystem", "label": "Plugin System", "file_type": "document", "source_file": "ROADMAP.md", "source_location": null, "source_url": null, "captured_at": null, "author": null, "contributor": null}, {"id": "roadmap_Webhooks", "label": "Webhook Notifications", "file_type": "document", "source_file": "ROADMAP.md", "source_location": null, "source_url": null, "captured_at": null, "author": null, "contributor": null}, {"id": "roadmap_SpotifyIntegration", "label": "Spotify Integration", "file_type": "document", "source_file": "ROADMAP.md", "source_location": null, "source_url": null, "captured_at": null, "author": null, "contributor": null}, {"id": "roadmap_CustomCSS", "label": "Custom CSS Overlay", "file_type": "document", "source_file": "ROADMAP.md", "source_location": null, "source_url": null, "captured_at": null, "author": null, "contributor": null}], "edges": [{"source": "roadmap_SFXAlerts", "target": "overlay_playSfx", "relation": "references", "confidence": "INFERRED", "confidence_score": 0.85, "source_file": "ROADMAP.md", "source_location": null, "weight": 1.0}, {"source": "roadmap_WelcomeMessages", "target": "readme_TikTokAIStreamer", "relation": "references", "confidence": "INFERRED", "confidence_score": 0.8, "source_file": "ROADMAP.md", "source_location": null, "weight": 1.0}, {"source": "roadmap_Leaderboard", "target": "readme_TikTokAIStreamer", "relation": "references", "confidence": "INFERRED", "confidence_score": 0.8, "source_file": "ROADMAP.md", "source_location": null, "weight": 1.0}, {"source": "roadmap_PointsSystem", "target": "readme_TikTokAIStreamer", "relation": "references", "confidence": "INFERRED", "confidence_score": 0.8, "source_file": "ROADMAP.md", "source_location": null, "weight": 1.0}, {"source": "roadmap_BackupSystem", "target": "readme_ConfigModule", "relation": "references", "confidence": "INFERRED", "confidence_score": 0.7, "source_file": "ROADMAP.md", "source_location": null, "weight": 1.0}, {"source": "roadmap_OBSWebSocket", "target": "readme_OBSOverlay", "relation": "references", "confidence": "INFERRED", "confidence_score": 0.85, "source_file": "ROADMAP.md", "source_location": null, "weight": 1.0}, {"source": "roadmap_CustomCSS", "target": "readme_OBSOverlay", "relation": "references", "confidence": "INFERRED", "confidence_score": 0.85, "source_file": "ROADMAP.md", "source_location": null, "weight": 1.0}, {"source": "roadmap_PluginSystem", "target": "readme_TikTokAIStreamer", "relation": "references", "confidence": "INFERRED", "confidence_score": 0.8, "source_file": "ROADMAP.md", "source_location": null, "weight": 1.0}, {"source": "roadmap_Webhooks", "target": "readme_TikTokAIStreamer", "relation": "references", "confidence": "INFERRED", "confidence_score": 0.8, "source_file": "ROADMAP.md", "source_location": null, "weight": 1.0}, {"source": "roadmap_SpotifyIntegration", "target": "readme_TikTokAIStreamer", "relation": "references", "confidence": "INFERRED", "confidence_score": 0.8, "source_file": "ROADMAP.md", "source_location": null, "weight": 1.0}, {"source": "readme_EventOrchestrator", "target": "panel_renderRules", "relation": "shares_data_with", "confidence": "INFERRED", "confidence_score": 0.7, "source_file": "ROADMAP.md", "source_location": null, "weight": 1.0}, {"source": "roadmap_SecurityFeatures", "target": "readme_PanelPassword", "relation": "references", "confidence": "INFERRED", "confidence_score": 0.85, "source_file": "ROADMAP.md", "source_location": null, "weight": 1.0}, {"source": "roadmap_StabilityFeatures", "target": "readme_TikTokAIStreamer", "relation": "references", "confidence": "INFERRED", "confidence_score": 0.8, "source_file": "ROADMAP.md", "source_location": null, "weight": 1.0}, {"source": "roadmap_UXUIFeatures", "target": "panel_showToast", "relation": "references", "confidence": "INFERRED", "confidence_score": 0.8, "source_file": "ROADMAP.md", "source_location": null, "weight": 1.0}], "hyperedges": []}